wagtail_react_streamfield/__init__.py
wagtail_react_streamfield/apps.py
wagtail_react_streamfield/edit_handlers.py
wagtail_react_streamfield/exceptions.py
wagtail_react_streamfield/monkey_patch.py
wagtail_react_streamfield/widgets.py
wagtail_react_streamfield/blocks/__init__.py
wagtail_react_streamfield/blocks/block.py
wagtail_react_streamfield/blocks/field_block.py
wagtail_react_streamfield/blocks/list_block.py
wagtail_react_streamfield/blocks/static_block.py
wagtail_react_streamfield/blocks/stream_block.py
wagtail_react_streamfield/blocks/struct_block.py
wagtail_react_streamfield/static/css/wagtail-react-streamfield.css
wagtail_react_streamfield/static/js/wagtail-react-streamfield.js
wagtail_react_streamfield/static/table_block/js/table.js
wagtail_react_streamfield/static/wagtailadmin/fonts/wagtail.woff
wagtail_react_streamfield/static/wagtailadmin/js/hallo-bootstrap.js
wagtail_react_streamfield/static/wagtailadmin/js/page-chooser.js
wagtail_react_streamfield/static/wagtaildocs/js/document-chooser.js
wagtail_react_streamfield/static/wagtailimages/js/image-chooser.js
wagtail_react_streamfield/static/wagtailsnippets/js/snippet-chooser.js
wagtail_react_streamfield/static_src/js/entry.js
wagtail_react_streamfield/templates/wagtailadmin/block_forms/blocks_container.html
wagtail_react_streamfield-1.3.6.dist-info/LICENSE
wagtail_react_streamfield-1.3.6.dist-info/METADATA
wagtail_react_streamfield-1.3.6.dist-info/WHEEL
wagtail_react_streamfield-1.3.6.dist-info/top_level.txt
wagtail_react_streamfield-1.3.6.dist-info/RECORD
